cryptic/__init__.py
cryptic/config.py
cryptic/database.py
cryptic/debug.py
cryptic/error_decorator.py
cryptic/errors.py
cryptic/jsonreader.py
cryptic/microservice.py
cryptic_game-0.5.4.dist-info/LICENSE
cryptic_game-0.5.4.dist-info/METADATA
cryptic_game-0.5.4.dist-info/WHEEL
cryptic_game-0.5.4.dist-info/top_level.txt
cryptic_game-0.5.4.dist-info/RECORD
