Metadata-Version: 2.1
Name: cryptic-game
Version: 0.5.4
Summary: Microservice handler for cryptic-game
Home-page: https://github.com/cryptic-game/python3-lib
Author: cryptic-game
Author-email: faq@cryptic-game.net
License: UNKNOWN
Platform: UNKNOWN
Requires-Dist: uuid
Requires-Dist: SQLAlchemy
Requires-Dist: PyMySQL
Requires-Dist: pyscheme
Requires-Dist: sentry-sdk
